mksci_font/__init__.py
mksci_font/data/SimSun.ttf
mksci_font/data/SunTimes.ttf
mksci_font/data/Times.ttf
mksci_font/data/merge_fonts.ff
mksci_font/font_wrapper.py
mksci_font-0.1.4.dist-info/LICENSE
mksci_font-0.1.4.dist-info/METADATA
mksci_font-0.1.4.dist-info/WHEEL
mksci_font-0.1.4.dist-info/RECORD
