Metadata-Version: 2.1
Name: mksci-font
Version: 0.1.4
Summary: 方便地将 Matplotlib 支持中文字体允许您配置图形为“中文宋体、英文 Times New Roman”
Author: Shuang Song
Author-email: songshgeo@gmail.com
Requires-Python: >=3.8.1
Classifier: Programming Language :: Python :: 3
Classifier: Programming Language :: Python :: 3.9
Classifier: Programming Language :: Python :: 3.10
Classifier: Programming Language :: Python :: 3.11
Classifier: Programming Language :: Python :: 3.12
Classifier: Programming Language :: Python :: 3.13
Requires-Dist: matplotlib
